graftpress_cli
